pmsm_pm_temp_predict/__init__.py
pmsm_pm_temp_predict/prediction.py
pmsm_pm_temp_predict/data/minmax_scaler.pkl
pmsm_pm_temp_predict/data/std_scaler.pkl
pmsm_pm_temp_predict-0.0.6.dist-info/METADATA
pmsm_pm_temp_predict-0.0.6.dist-info/WHEEL
pmsm_pm_temp_predict-0.0.6.dist-info/top_level.txt
pmsm_pm_temp_predict-0.0.6.dist-info/RECORD
