Metadata-Version: 2.1
Name: pmsm-pm-temp-predict
Version: 0.0.6
Summary: Permanent magnet temperature prediction
Home-page: UNKNOWN
Author: Oleksandr
Author-email: <oleksandr.ohlashennyi.knm.2020@lpnu.ua>
License: UNKNOWN
Keywords: python,pmsm,motor,temperatue,prediction
Platform: UNKNOWN
Classifier: Development Status :: 3 - Alpha
Classifier: Intended Audience :: Education
Classifier: Programming Language :: Python :: 3
Classifier: Operating System :: Microsoft :: Windows
Requires-Dist: pandas
Requires-Dist: sklearn
Requires-Dist: numpy
Requires-Dist: filesplit
